pdf_invoice_util/__init__.py
pdf_invoice_util/config.py
pdf_invoice_util/invoice.py
pdf_invoice_util/invoice_pdf.py
pdf_invoice_util/pdf.py
pdf_invoice_util/test/test_config.py
pdf_invoice_util/test/test_invoice.py
pdf_invoice_util/test/test_invoice_pdf.py
pdf_invoice_util-0.0.4.dist-info/LICENSE
pdf_invoice_util-0.0.4.dist-info/METADATA
pdf_invoice_util-0.0.4.dist-info/WHEEL
pdf_invoice_util-0.0.4.dist-info/top_level.txt
pdf_invoice_util-0.0.4.dist-info/RECORD
