Metadata-Version: 2.2
Name: pdf_invoice_util
Version: 0.0.4
Author-email: Geert Selderslaghs <geert.selderslaghs@gmail.com>
License: MIT License
Project-URL: Repository, https://github.com/gselderslaghs/pdf-invoice-util.git
Project-URL: Bug Tracker, https://github.com/gselderslaghs/pdf-invoice-util/issues
Requires-Python: >=3.8
License-File: LICENSE
Requires-Dist: pyyaml>=6.0
Requires-Dist: fpdf2>=2.8
